<KinBody name="obstacles">
    <RotationAxis>0 0 0 0</RotationAxis>
    <Translation>0 0 0.2</Translation>
    <Body name=" 0 " type="static">
        <Geom type="box">
            <Extents> 0.245103498604 0.123173003691  0.1</Extents>
            <RotationAxis> 0 0 1  124.76868225 </RotationAxis>
            <Translation> -2.50577326789 2.91202259472  0</Translation>
            <diffuseColor>1 1 1</diffuseColor>
        </Geom>
    </Body>

    <Body name=" 1 " type="static">
        <Geom type="cylinder">
            <radius> 0.700554827257 </radius>
            <height>0.2</height>
            <Translation> 1.27690585296 -3.94097793281  0</Translation>
            <RotationAxis>1 0 0 90</RotationAxis>
            <diffuseColor>1 1 1</diffuseColor>
        </Geom>
    </Body>
    <Body name=" 2 " type="static">
        <Geom type="box">
            <Extents> 0.752059111485 0.240991589481  0.1</Extents>
            <RotationAxis> 0 0 1  131.954680122 </RotationAxis>
            <Translation> -3.52286455628 -2.77496483484  0</Translation>
            <diffuseColor>1 1 1</diffuseColor>
        </Geom>
    </Body>

    <Body name=" 3 " type="static">
        <Geom type="cylinder">
            <radius> 0.266702580302 </radius>
            <height>0.2</height>
            <Translation> 0.774024765636 3.95582522551  0</Translation>
            <RotationAxis>1 0 0 90</RotationAxis>
            <diffuseColor>1 1 1</diffuseColor>
        </Geom>
    </Body>
    <Body name=" 4 " type="static">
        <Geom type="box">
            <Extents> 0.871293525918 0.839037154033  0.1</Extents>
            <RotationAxis> 0 0 1  63.469509287 </RotationAxis>
            <Translation> 2.11276253133 0.199732035693  0</Translation>
            <diffuseColor>1 1 1</diffuseColor>
        </Geom>
    </Body>

    <Body name=" 5 " type="static">
        <Geom type="cylinder">
            <radius> 0.86078217167 </radius>
            <height>0.2</height>
            <Translation> -1.10260542773 0.824819940715  0</Translation>
            <RotationAxis>1 0 0 90</RotationAxis>
            <diffuseColor>1 1 1</diffuseColor>
        </Geom>
    </Body>
    <Body name=" 6 " type="static">
        <Geom type="box">
            <Extents> 0.247648212275 0.402067171243  0.1</Extents>
            <RotationAxis> 0 0 1  110.205941104 </RotationAxis>
            <Translation> 2.61643937731 -2.30566224747  0</Translation>
            <diffuseColor>1 1 1</diffuseColor>
        </Geom>
    </Body>

    <Body name=" 7 " type="static">
        <Geom type="cylinder">
            <radius> 0.116077034041 </radius>
            <height>0.2</height>
            <Translation> -1.50743358159 2.26540125925  0</Translation>
            <RotationAxis>1 0 0 90</RotationAxis>
            <diffuseColor>1 1 1</diffuseColor>
        </Geom>
    </Body>
    <Body name=" 8 " type="static">
        <Geom type="box">
            <Extents> 0.239481421034 0.434039655207  0.1</Extents>
            <RotationAxis> 0 0 1  6.56706091323 </RotationAxis>
            <Translation> -0.00411267945754 -1.83264259804  0</Translation>
            <diffuseColor>1 1 1</diffuseColor>
        </Geom>
    </Body>

    <Body name=" 9 " type="static">
        <Geom type="cylinder">
            <radius> 0.429870089272 </radius>
            <height>0.2</height>
            <Translation> -1.27619296101 -3.44477468199  0</Translation>
            <RotationAxis>1 0 0 90</RotationAxis>
            <diffuseColor>1 1 1</diffuseColor>
        </Geom>
    </Body>
    <Body name=" 10 " type="static">
        <Geom type="box">
            <Extents> 0.554488331184 0.538721598293  0.1</Extents>
            <RotationAxis> 0 0 1  70.4958047293 </RotationAxis>
            <Translation> -3.83128059246 -1.21467021894  0</Translation>
            <diffuseColor>1 1 1</diffuseColor>
        </Geom>
    </Body>

    <Body name=" 11 " type="static">
        <Geom type="cylinder">
            <radius> 0.741851226922 </radius>
            <height>0.2</height>
            <Translation> 3.76206929412 -2.01057494971  0</Translation>
            <RotationAxis>1 0 0 90</RotationAxis>
            <diffuseColor>1 1 1</diffuseColor>
        </Geom>
    </Body>
    <Body name=" 12 " type="static">
        <Geom type="box">
            <Extents> 0.344059942304 0.569004112389  0.1</Extents>
            <RotationAxis> 0 0 1  92.930759384 </RotationAxis>
            <Translation> -3.56379190321 1.07740677844  0</Translation>
            <diffuseColor>1 1 1</diffuseColor>
        </Geom>
    </Body>

    <Body name=" 13 " type="static">
        <Geom type="cylinder">
            <radius> 0.616369347715 </radius>
            <height>0.2</height>
            <Translation> 3.35588197694 -3.54217475669  0</Translation>
            <RotationAxis>1 0 0 90</RotationAxis>
            <diffuseColor>1 1 1</diffuseColor>
        </Geom>
    </Body>
    <Body name=" 14 " type="static">
        <Geom type="box">
            <Extents> 0.70286492365 0.3262422434  0.1</Extents>
            <RotationAxis> 0 0 1  1.8363563623 </RotationAxis>
            <Translation> 0.865896804935 1.85751061835  0</Translation>
            <diffuseColor>1 1 1</diffuseColor>
        </Geom>
    </Body>

    <Body name=" 15 " type="static">
        <Geom type="cylinder">
            <radius> 0.112109101112 </radius>
            <height>0.2</height>
            <Translation> -2.80005186606 1.29600219582  0</Translation>
            <RotationAxis>1 0 0 90</RotationAxis>
            <diffuseColor>1 1 1</diffuseColor>
        </Geom>
    </Body>
    <Body name=" 16 " type="static">
        <Geom type="box">
            <Extents> 0.530471503699 0.19559694364  0.1</Extents>
            <RotationAxis> 0 0 1  37.5036628696 </RotationAxis>
            <Translation> -2.78446006677 -3.72226367734  0</Translation>
            <diffuseColor>1 1 1</diffuseColor>
        </Geom>
    </Body>

    <Body name=" 17 " type="static">
        <Geom type="cylinder">
            <radius> 0.507082363881 </radius>
            <height>0.2</height>
            <Translation> 1.86036611174 2.06219862247  0</Translation>
            <RotationAxis>1 0 0 90</RotationAxis>
            <diffuseColor>1 1 1</diffuseColor>
        </Geom>
    </Body>
</KinBody>
